torchflows/__init__.py
torchflows/_version.py
torchflows/architectures.py
torchflows/flows.py
torchflows/regularization.py
torchflows/utils.py
torchflows/base_distributions/__init__.py
torchflows/base_distributions/cauchy.py
torchflows/base_distributions/concatenation.py
torchflows/base_distributions/gaussian.py
torchflows/base_distributions/mixture.py
torchflows/bijections/__init__.py
torchflows/bijections/base.py
torchflows/bijections/numerical_inversion.py
torchflows/bijections/continuous/__init__.py
torchflows/bijections/continuous/base.py
torchflows/bijections/continuous/ddnf.py
torchflows/bijections/continuous/ffjord.py
torchflows/bijections/continuous/layers.py
torchflows/bijections/continuous/otflow.py
torchflows/bijections/continuous/rnode.py
torchflows/bijections/finite/__init__.py
torchflows/bijections/finite/__matrix.py
torchflows/bijections/finite/autoregressive/__init__.py
torchflows/bijections/finite/autoregressive/architectures.py
torchflows/bijections/finite/autoregressive/layers.py
torchflows/bijections/finite/autoregressive/layers_base.py
torchflows/bijections/finite/autoregressive/util.py
torchflows/bijections/finite/autoregressive/conditioning/__init__.py
torchflows/bijections/finite/autoregressive/conditioning/context.py
torchflows/bijections/finite/autoregressive/conditioning/coupling_masks.py
torchflows/bijections/finite/autoregressive/conditioning/transforms.py
torchflows/bijections/finite/autoregressive/transformers/__init__.py
torchflows/bijections/finite/autoregressive/transformers/base.py
torchflows/bijections/finite/autoregressive/transformers/combination/__init__.py
torchflows/bijections/finite/autoregressive/transformers/combination/base.py
torchflows/bijections/finite/autoregressive/transformers/combination/sigmoid.py
torchflows/bijections/finite/autoregressive/transformers/combination/sigmoid_util.py
torchflows/bijections/finite/autoregressive/transformers/integration/__init__.py
torchflows-1.2.0.dist-info/licenses/LICENSE
torchflows-1.2.0.dist-info/METADATA
torchflows-1.2.0.dist-info/WHEEL
torchflows-1.2.0.dist-info/top_level.txt
torchflows-1.2.0.dist-info/RECORD
