Metadata-Version: 2.4
Name: torchflows
Version: 1.2.0
Summary: Normalizing flows in PyTorch
Home-page: https://github.com/davidnabergoj/torchflows
Author: David Nabergoj
Author-email: David Nabergoj <david.nabergoj@fri.uni-lj.si>
Project-URL: Homepage, https://github.com/davidnabergoj/torchflows
Project-URL: Issues, https://github.com/davidnabergoj/torchflows/issues
Classifier: Programming Language :: Python :: 3
Classifier: License :: OSI Approved :: MIT License
Classifier: Operating System :: OS Independent
Requires-Python: >=3.7, <4
License-File: LICENSE
Requires-Dist: torch>=2.0.1
Requires-Dist: numpy
Requires-Dist: torchdiffeq>=0.2.3
Requires-Dist: tqdm>=4.65.0
Dynamic: author
Dynamic: home-page
Dynamic: license-file
Dynamic: requires-python
